pyswell/__init__.py
pyswell/skeleton.py
pyswell-0.0.1.dist-info/AUTHORS.rst
pyswell-0.0.1.dist-info/LICENSE.txt
pyswell-0.0.1.dist-info/METADATA
pyswell-0.0.1.dist-info/WHEEL
pyswell-0.0.1.dist-info/entry_points.txt
pyswell-0.0.1.dist-info/top_level.txt
pyswell-0.0.1.dist-info/RECORD
